LICENSE
MANIFEST.in
README.md
setup.cfg
setup.py
syncmatrix/__init__.py
syncmatrix/client.py
syncmatrix/config.toml
syncmatrix/configuration.py
syncmatrix/environments.py
syncmatrix/schedules.py
syncmatrix/signals.py
syncmatrix/triggers.py
syncmatrix.egg-info/PKG-INFO
syncmatrix.egg-info/SOURCES.txt
syncmatrix.egg-info/dependency_links.txt
syncmatrix.egg-info/entry_points.txt
syncmatrix.egg-info/requires.txt
syncmatrix.egg-info/top_level.txt
syncmatrix/cli/__init__.py
syncmatrix/cli/auth.py
syncmatrix/cli/namespaces.py
syncmatrix/cli/users.py
syncmatrix/core/__init__.py
syncmatrix/core/edge.py
syncmatrix/core/flow.py
syncmatrix/core/task.py
syncmatrix/engine/__init__.py
syncmatrix/engine/flow_runner.py
syncmatrix/engine/state.py
syncmatrix/engine/task_runner.py
syncmatrix/engine/executors/__init__.py
syncmatrix/engine/executors/base.py
syncmatrix/engine/executors/concurrent.py
syncmatrix/engine/executors/distributed.py
syncmatrix/engine/executors/local.py
syncmatrix/flows/__init__.py
syncmatrix/tasks/__init__.py
syncmatrix/tasks/flow_runner_task.py
syncmatrix/tasks/strings.py
syncmatrix/tasks/control_flow/__init__.py
syncmatrix/tasks/control_flow/approval.py
syncmatrix/tasks/control_flow/conditional.py
syncmatrix/tasks/control_flow/resume.py
syncmatrix/tasks/core/__init__.py
syncmatrix/tasks/core/collections.py
syncmatrix/tasks/core/constants.py
syncmatrix/tasks/core/function_task.py
syncmatrix/tasks/core/operators.py
syncmatrix/tasks/notifications/__init__.py
syncmatrix/tasks/notifications/email_task.py
syncmatrix/utilities/__init__.py
syncmatrix/utilities/collections.py
syncmatrix/utilities/context.py
syncmatrix/utilities/datetimes.py
syncmatrix/utilities/flows.py
syncmatrix/utilities/functions.py
syncmatrix/utilities/json.py
syncmatrix/utilities/strings.py
syncmatrix/utilities/tasks.py
syncmatrix/utilities/tests.py
tests/__init__.py
tests/test_configuration.py
tests/test_context.py
tests/test_schedules.py
tests/test_setup.py
tests/test_signals.py
tests/test_triggers.py
tests/core/__init__.py
tests/core/test_flow.py
tests/core/test_task.py
tests/engine/__init__.py
tests/engine/test_flow_runner.py
tests/engine/test_state.py
tests/engine/test_task_runner.py
