Metadata-Version: 2.4
Name: syncmatrix
Version: 0.2.1
Home-page: https://www.github.com/khulnasoft/syncmatrix
Author: Md Sulaiman
Author-email: dev.sulaiman@icloud.com
License-File: LICENSE
Requires-Dist: click
Requires-Dist: croniter
Requires-Dist: cryptography
Requires-Dist: distributed>=1.16.1
Requires-Dist: graphviz
Requires-Dist: jsonpickle
Requires-Dist: mypy_extensions
Requires-Dist: python-dateutil
Requires-Dist: requests
Requires-Dist: wrapt
Requires-Dist: toml
Requires-Dist: typing
Requires-Dist: typing_extensions
Provides-Extra: dev
Requires-Dist: pytest; extra == "dev"
Requires-Dist: pytest-env; extra == "dev"
Requires-Dist: pytest-xdist; extra == "dev"
Dynamic: author
Dynamic: author-email
Dynamic: description
Dynamic: home-page
Dynamic: license-file
Dynamic: provides-extra
Dynamic: requires-dist
